LICENSE
MANIFEST.in
README.rst
setup.py
pygments_pprint_sql/__init__.py
pygments_pprint_sql/tests.py
pygments_pprint_sql.egg-info/PKG-INFO
pygments_pprint_sql.egg-info/SOURCES.txt
pygments_pprint_sql.egg-info/dependency_links.txt
pygments_pprint_sql.egg-info/entry_points.txt
pygments_pprint_sql.egg-info/requires.txt
pygments_pprint_sql.egg-info/top_level.txt