Metadata-Version: 1.1
Name: pygments-pprint-sql
Version: 0.1.0
Summary: Pretty format your SQL queries for easier reading.
Home-page: http://github.com/natedub/pygments-pprint-sql
Author: Nathan Wright
Author-email: thatnateguy@gmail.com
License: BSD
Platform: UNKNOWN
Classifier: Development Status :: 4 - Beta
Classifier: Programming Language :: Python
Classifier: Intended Audience :: Developers
